{
  "name": "apicurio-registry-gitops-example",
  "full_name": "Apicurio/apicurio-registry-gitops-example",
  "description": null,
  "created_at": "2026-04-09T13:31:05+00:00",
  "updated_at": "2026-07-16T16:58:45+00:00",
  "stars": 0,
  "forks": 2,
  "watchers": 0,
  "open_issues": 0,
  "language": "TypeScript",
  "topics": [],
  "license": "Apache License 2.0",
  "homepage": null,
  "has_wiki": true,
  "has_discussions": null,
  "top_contributing_companies": [
    {
      "company": "Red Hat",
      "commits": 12,
      "percentage": 92.31
    },
    {
      "company": "Fossas",
      "commits": 1,
      "percentage": 7.69
    }
  ],
  "extracted_at": "2026-07-22T17:00:44.720605"
}